devin_cli/__init__.py
devin_cli/cli.py
devin_cli/config.py
devin_cli/api/__init__.py
devin_cli/api/attachments.py
devin_cli/api/client.py
devin_cli/api/knowledge.py
devin_cli/api/playbooks.py
devin_cli/api/secrets.py
devin_cli/api/sessions.py
devin_cli-0.0.8.dist-info/METADATA
devin_cli-0.0.8.dist-info/WHEEL
devin_cli-0.0.8.dist-info/entry_points.txt
devin_cli-0.0.8.dist-info/licenses/LICENSE
devin_cli-0.0.8.dist-info/RECORD
