Metadata-Version: 2.4
Name: devin-cli
Version: 0.0.8
Summary: Unofficial CLI for Devin AI - The first AI Software Engineer
Project-URL: Homepage, https://github.com/revanthpobala/devin-cli
Project-URL: Repository, https://github.com/revanthpobala/devin-cli.git
Project-URL: Issues, https://github.com/revanthpobala/devin-cli/issues
Author-email: revanth <revanth@example.com>
License-Expression: MIT
License-File: LICENSE
Keywords: agent,ai,automation,autonomous,cli,cognition,devin,software-engineer,terminal
Classifier: Development Status :: 4 - Beta
Classifier: Environment :: Console
Classifier: Intended Audience :: Developers
Classifier: License :: OSI Approved :: MIT License
Classifier: Operating System :: OS Independent
Classifier: Programming Language :: Python :: 3
Classifier: Programming Language :: Python :: 3.9
Classifier: Programming Language :: Python :: 3.10
Classifier: Programming Language :: Python :: 3.11
Classifier: Programming Language :: Python :: 3.12
Classifier: Topic :: Scientific/Engineering :: Artificial Intelligence
Classifier: Topic :: Software Development :: Build Tools
Requires-Python: >=3.9
Requires-Dist: httpx>=0.27.0
Requires-Dist: pyyaml>=6.0
Requires-Dist: rich>=13.0.0
Requires-Dist: typer[all]>=0.9.0
Provides-Extra: dev
Requires-Dist: build; extra == 'dev'
Requires-Dist: pytest-cov>=4.0.0; extra == 'dev'
Requires-Dist: pytest>=7.0; extra == 'dev'
Requires-Dist: respx>=0.20.0; extra == 'dev'
Requires-Dist: twine; extra == 'dev'
